phlocation/CHANGELOG.txt
phlocation/LICENCE.txt
phlocation/README.txt
phlocation/__init__.py
phlocation/admin.py
phlocation/apps.py
phlocation/forms.py
phlocation/models.py
phlocation/serializers.py
phlocation/setup.py
phlocation/tests.py
phlocation/urls.py
phlocation/views.py
phlocation/__pycache__/__init__.cpython-38.pyc
phlocation/__pycache__/admin.cpython-38.pyc
phlocation/__pycache__/forms.cpython-38.pyc
phlocation/__pycache__/models.cpython-38.pyc
phlocation/__pycache__/serializers.cpython-38.pyc
phlocation/__pycache__/tests.cpython-38.pyc
phlocation/__pycache__/urls.cpython-38.pyc
phlocation/__pycache__/views.cpython-38.pyc
phlocation/build/lib/phlocation/__init__.py
phlocation/build/lib/phlocation/admin.py
phlocation/build/lib/phlocation/apps.py
phlocation/build/lib/phlocation/forms.py
phlocation/build/lib/phlocation/models.py
phlocation/build/lib/phlocation/serializers.py
phlocation/build/lib/phlocation/tests.py
phlocation/build/lib/phlocation/urls.py
phlocation/build/lib/phlocation/views.py
phlocation/build/lib/phlocation/migrations/0001_initial.py
phlocation/build/lib/phlocation/migrations/__init__.py
phlocation/fixtures/ph_locations.json
phlocation/migrations/0001_initial.py
phlocation/migrations/__init__.py
phlocation/migrations/__pycache__/0001_initial.cpython-38.pyc
phlocation/migrations/__pycache__/__init__.cpython-38.pyc
phlocation/ph_location.egg-info/SOURCES.txt
phlocation/ph_location.egg-info/dependency_links.txt
phlocation/ph_location.egg-info/top_level.txt
phlocation/phlocation/__init__.py
phlocation/phlocation/admin.py
phlocation/phlocation/apps.py
phlocation/phlocation/forms.py
phlocation/phlocation/models.py
phlocation/phlocation/serializers.py
phlocation/phlocation/tests.py
phlocation/phlocation/urls.py
phlocation/phlocation/views.py
phlocation/phlocation/fixtures/ph_locations.json
phlocation/phlocation/migrations/0001_initial.py
phlocation/phlocation/migrations/__init__.py
phlocation/static/phlocation/js/.DS_Store
phlocation/static/phlocation/js/phlocation.js
phlocation/templates/phlocation/widgets/select.html
ph_location-0.0.5.dist-info/LICENCE.txt
ph_location-0.0.5.dist-info/METADATA
ph_location-0.0.5.dist-info/WHEEL
ph_location-0.0.5.dist-info/top_level.txt
ph_location-0.0.5.dist-info/RECORD
